[
  {
    "button": "assets/solarSystem/jupiter.png",
    "buttonHeight": "100",
    "buttonKey": "button1",
    "buttonWidth": "100",
    "buttonX": "100",
    "buttonY": "50",
    "shadowColor": "0x000000",
    "modalData": {
      "includeBackground": true,
      "itemsArr": [
        {
          "content": "modalBG",
          "contentScale": 1,
          "height": "150",
          "type": "image",
          "width": "300"
        },
        {
          "content": "Jupiter",
          "fontSize": "15",
          "offsetY": "-50",
          "type": "text",
          "wordWrapWidth": "250"
        },
        {
          "content": "Seriously???",
          "fontSize": "11",
          "offsetY": "50",
          "type": "text"
        }
      ],
      "modalCloseOnInput": true,
      "type": "modal1"
    }
  },
  {
    "button": "assets/solarSystem/mars.png",
    "buttonHeight": "100",
    "buttonKey": "button2",
    "buttonWidth": "100",
    "buttonX": "300",
    "buttonY": "50",
    "shadowColor": "0x000000",
    "modalData": {
      "includeBackground": true,
      "itemsArr": [
        {
          "content": "modalBG",
          "contentScale": "1",
          "height": "150",
          "type": "image",
          "width": "300"
        },
        {
          "content": "Mars",
          "fontSize": "15",
          "offsetY": "-50",
          "type": "text",
          "wordWrapWidth": "250"
        },
        {
          "content": "Seriously???",
          "fontSize": "11",
          "offsetY": "50",
          "type": "text"
        }
      ],
      "modalCloseOnInput": true,
      "type": "modal2"
    }
  },
  {
    "button": "assets/solarSystem/mercury.png",
    "buttonHeight": "100",
    "buttonKey": "button3",
    "buttonWidth": "100",
    "buttonX": "100",
    "buttonY": "150",
    "shadowColor": "0x000000",
    "modalData": {
      "includeBackground": true,
      "itemsArr": [
        {
          "content": "modalBG",
          "contentScale": "1",
          "height": "150",
          "type": "image",
          "width": "300"
        },
        {
          "content": "Mercury",
          "fontSize": "15",
          "offsetY": "-50",
          "type": "text",
          "wordWrapWidth": "250"
        },
        {
          "content": "Seriously???",
          "fontSize": "11",
          "offsetY": "50",
          "type": "text"
        }
      ],
      "modalCloseOnInput": true,
      "type": "modal3"
    }
  },
  {
    "button": "assets/solarSystem/earth.png",
    "buttonHeight": "100",
    "buttonKey": "button4",
    "buttonWidth": "100",
    "buttonX": "300",
    "buttonY": "150",
    "shadowColor": "0x000000",
    "modalData": {
      "includeBackground": true,
      "itemsArr": [
        {
          "content": "modalBG",
          "contentScale": "1",
          "height": "150",
          "type": "image",
          "width": "300"
        },
        {
          "content": "Earth",
          "fontSize": "15",
          "offsetY": "-50",
          "type": "text",
          "wordWrapWidth": "250"
        },
        {
          "content": "Seriously???",
          "fontSize": "11",
          "offsetY": "50",
          "type": "text"
        }
      ],
      "modalCloseOnInput": true,
      "type": "modal4"
    }
  }
]